colorism/__init__.py
colorism/color.py
colorism/converter.py
colorism-1.1.2.dist-info/LICENSE
colorism-1.1.2.dist-info/METADATA
colorism-1.1.2.dist-info/WHEEL
colorism-1.1.2.dist-info/top_level.txt
colorism-1.1.2.dist-info/RECORD
