Metadata-Version: 2.1
Name: colorism
Version: 1.1.2
Summary: A Python package for color formatting in the terminal.
Home-page: https://github.com/federikowsky/Colorism
Author: federikowsky
License: MIT
Classifier: Development Status :: 3 - Alpha
Classifier: Intended Audience :: Developers
Classifier: License :: OSI Approved :: MIT License
Classifier: Programming Language :: Python :: 3
Classifier: Programming Language :: Python :: 3.6
Classifier: Programming Language :: Python :: 3.7
Classifier: Programming Language :: Python :: 3.8
License-File: LICENSE
